<?xml version="1.0" encoding="UTF-8"?>
<!DOCTYPE suite SYSTEM "https://testng.org/testng-1.0.dtd">
<suite name="Suite">	
	<test name="Test home page outsource readmore button on Chrome">
		<parameter name="browserName" value="Chrome" />
		<parameter name="author" value="Uditha" />
		<classes>
			<class name="com.duosasinos.testcases.HomePageTest">
				<methods>
					<include name="TestOutsourceReadmorebutton" />
				</methods>
			</class>
		</classes>
	</test> <!-- Test -->	
	<test name="Test home page outsource readmore button on Firefox">
		<parameter name="browserName" value="Firefox" />
		<parameter name="author" value="Uditha" />
		<classes>
			<class name="com.duosasinos.testcases.HomePageTest">
				<methods>
					<include name="TestOutsourceReadmorebutton" />
				</methods>
			</class>
		</classes>
	</test> <!-- Test -->
	<test name="Test home page outsource readmore button on Edge">
		<parameter name="browserName" value="Edge" />
		<parameter name="author" value="Uditha" />
		<classes>
			<class name="com.duosasinos.testcases.HomePageTest">
				<methods>
					<include name="TestOutsourceReadmorebutton" />
				</methods>
			</class>
		</classes>
	</test> <!-- Test -->
</suite> <!-- Suite -->